draftjs_exporter_markdown/__init__.py
draftjs_exporter_markdown/blocks.py
draftjs_exporter_markdown/code.py
draftjs_exporter_markdown/engine.py
draftjs_exporter_markdown/entities.py
draftjs_exporter_markdown/lists.py
draftjs_exporter_markdown/markdown.py
draftjs_exporter_markdown/styles.py
draftjs_exporter_markdown-0.2.4.dist-info/LICENSE
draftjs_exporter_markdown-0.2.4.dist-info/METADATA
draftjs_exporter_markdown-0.2.4.dist-info/WHEEL
draftjs_exporter_markdown-0.2.4.dist-info/top_level.txt
draftjs_exporter_markdown-0.2.4.dist-info/RECORD
