Metadata-Version: 2.1
Name: draftjs-exporter-markdown
Version: 0.2.4
Summary: Library to convert rich text from Draft.js raw ContentState to Markdown, based on draftjs_exporter
Home-page: https://github.com/thibaudcolas/draftjs_exporter_markdown
Author: Thibaud Colas
Author-email: thibaudcolas@gmail.com
License: MIT
Keywords: draftjs,exporter,markdown,content
Platform: UNKNOWN
Classifier: Environment :: Web Environment
Classifier: Intended Audience :: Developers
Classifier: License :: OSI Approved :: MIT License
Classifier: Operating System :: OS Independent
Classifier: Programming Language :: Python
Classifier: Programming Language :: Python :: 3
Classifier: Programming Language :: Python :: 3.6
Classifier: Topic :: Internet :: WWW/HTTP
Classifier: Topic :: Internet :: WWW/HTTP :: Dynamic Content
Classifier: Topic :: Internet :: WWW/HTTP :: Site Management
Classifier: Topic :: Software Development :: Libraries :: Application Frameworks
Classifier: Topic :: Software Development :: Libraries :: Python Modules
Classifier: Topic :: Text Editors :: Word Processors
License-File: LICENSE
Requires-Dist: draftjs-exporter (<6,>=2.1.0)
